oidcop/__init__.py
oidcop/authn_event.py
oidcop/client_authn.py
oidcop/configure.py
oidcop/constant.py
oidcop/construct.py
oidcop/cookie_handler.py
oidcop/endpoint.py
oidcop/endpoint_context.py
oidcop/exception.py
oidcop/logging.py
oidcop/login_hint.py
oidcop/scopes.py
oidcop/server.py
oidcop/template_handler.py
oidcop/util.py
oidcop/utils.py
oidcop/authz/__init__.py
oidcop/oauth2/__init__.py
oidcop/oauth2/authorization.py
oidcop/oauth2/introspection.py
oidcop/oauth2/pushed_authorization.py
oidcop/oauth2/token.py
oidcop/oauth2/add_on/__init__.py
oidcop/oauth2/add_on/dpop.py
oidcop/oauth2/add_on/extra_args.py
oidcop/oidc/__init__.py
oidcop/oidc/authorization.py
oidcop/oidc/discovery.py
oidcop/oidc/provider_config.py
oidcop/oidc/read_registration.py
oidcop/oidc/registration.py
oidcop/oidc/session.py
oidcop/oidc/token.py
oidcop/oidc/userinfo.py
oidcop/oidc/add_on/__init__.py
oidcop/oidc/add_on/custom_scopes.py
oidcop/oidc/add_on/pkce.py
oidcop/session/__init__.py
oidcop/session/claims.py
oidcop/session/database.py
oidcop/session/grant.py
oidcop/session/info.py
oidcop/session/manager.py
oidcop/session/token.py
oidcop/token/__init__.py
oidcop/token/exception.py
oidcop/token/handler.py
oidcop/token/id_token.py
oidcop/token/jwt_token.py
oidcop/user_authn/__init__.py
oidcop/user_authn/authn_context.py
oidcop/user_authn/user.py
oidcop/user_info/__init__.py
oidcop-2.4.3.dist-info/LICENSE
oidcop-2.4.3.dist-info/METADATA
oidcop-2.4.3.dist-info/WHEEL
oidcop-2.4.3.dist-info/top_level.txt
oidcop-2.4.3.dist-info/RECORD
