Metadata-Version: 2.1
Name: oidcop
Version: 2.4.3
Summary: Python implementation of OIDC Provider
Home-page: https://github.com/IdentityPython/oidc-op
Author: Roland Hedberg
Author-email: roland@catalogix.se
License: Apache 2.0
Classifier: Development Status :: 5 - Production/Stable
Classifier: License :: OSI Approved :: Apache Software License
Classifier: Programming Language :: Python :: 3.6
Classifier: Programming Language :: Python :: 3.7
Classifier: Programming Language :: Python :: 3.8
Classifier: Programming Language :: Python :: 3.9
Classifier: Topic :: Software Development :: Libraries :: Python Modules
License-File: LICENSE
Requires-Dist: oidcmsg (==1.5.4)
Requires-Dist: pyyaml
Requires-Dist: jinja2 (>=2.11.3)
Requires-Dist: responses (>=0.13.0)
